avmp/__init__.py
avmp/core/VERSION
avmp/core/__init__.py
avmp/core/cli.py
avmp/core/exceptions.py
avmp/core/models.py
avmp/core/updater.py
avmp/core/wrapper.py
avmp/tools/__init__.py
avmp/tools/jira_tools.py
avmp/tools/python_tools.py
avmp/tools/slack_tools.py
avmp/tools/tenable_tools.py
avmp/utils/__init__.py
avmp/utils/ip_tools.py
avmp/utils/ip_tools_test.py
avmp/utils/logging_utils.py
avmp/utils/vuln_db.py
avmp-0.1.1.dist-info/entry_points.txt
avmp-0.1.1.dist-info/LICENSE
avmp-0.1.1.dist-info/WHEEL
avmp-0.1.1.dist-info/METADATA
avmp-0.1.1.dist-info/RECORD
