Metadata-Version: 2.1
Name: avmp
Version: 0.1.1
Summary: Command line vulnerability program manager.
Home-page: https://github.com/RackReaver/AVMP
License: Apache-2.0
Keywords: automation,jira,vulnerability-detection,vulnerability-management,vulnerability-scanners,vulnerability-assessment,tenable,vulnerability-scanning,tenableio
Author: RackReaver
Author-email: rackreaver@gmail.com
Requires-Python: >=3.9,<4.0
Classifier: License :: OSI Approved :: Apache Software License
Classifier: Programming Language :: Python :: 3
Classifier: Programming Language :: Python :: 3.10
Classifier: Programming Language :: Python :: 3.9
Requires-Dist: click (==7.1.2)
Requires-Dist: docopt (>=0.6.2,<0.7.0)
Requires-Dist: jira (==2.0.0)
Requires-Dist: pyTenable (==1.2.6)
Requires-Dist: requests (==2.25.1)
Project-URL: Repository, https://github.com/RackReaver/AVMP
